playlyfe_graphql/__init__.py
playlyfe_graphql/playlyfe.py
playlyfe_graphql-1.5.0.dist-info/DESCRIPTION.rst
playlyfe_graphql-1.5.0.dist-info/METADATA
playlyfe_graphql-1.5.0.dist-info/RECORD
playlyfe_graphql-1.5.0.dist-info/WHEEL
playlyfe_graphql-1.5.0.dist-info/metadata.json
playlyfe_graphql-1.5.0.dist-info/top_level.txt
