Metadata-Version: 2.0
Name: playlyfe-graphql
Version: 1.5.0
Summary: This is the official Playlyfe Python GraphQL API V3 SDK for the Playlyfe V3 API.
Home-page: https://github.com/playlyfe/playlyfe-python-graphql-sdk
Author: Peter John
Author-email: peter@playlyfe.com
License: UNKNOWN
Keywords: GraphQL,Playlyfe V3 API,Playlyfe SDK,Gamification
Platform: UNKNOWN
Requires-Dist: pyjwt (==1.4.0)
